[
  {
    "id": 1,
    "username": "user_one",
    "email": "one@email.com",
    "password": "gamer12345",
    "interestedGenre": "Shooter",
    "preferredPlatform": "PC",
    "aboutMe": "I love games"
  },
  {
    "id": 2,
    "username": "user_two",
    "email": "two@email.com",
    "password": "gamer12345",
    "interestedGenre": "Survival",
    "preferredPlatform": "PC",
    "aboutMe": "Gaming is my passion"
  },
  {
    "id": 3,
    "username": "user_three",
    "email": "three@email.com",
    "password": "gamer12345",
    "interestedGenre": "Sports",
    "preferredPlatform": "PC",
    "aboutMe": "Gaming woohoo"
  },
  {
    "id": 4,
    "username": "user_four",
    "email": "four@email.com",
    "password": "gamer12345",
    "interestedGenre": "Anime",
    "preferredPlatform": "PC",
    "aboutMe": "Games 4 life"
  },
  {
    "id": 5,
    "username": "user_five",
    "email": "five@email.com",
    "password": "gamer12345",
    "interestedGenre": "Survival",
    "preferredPlatform": "Console",
    "aboutMe": "I love free"
  }
]
